draw_with_percentage/__init__.py
draw_with_percentage/draw_with_percentage.py
draw_with_percentage-0.0.6.dist-info/LICENCE
draw_with_percentage-0.0.6.dist-info/METADATA
draw_with_percentage-0.0.6.dist-info/WHEEL
draw_with_percentage-0.0.6.dist-info/top_level.txt
draw_with_percentage-0.0.6.dist-info/RECORD
