Metadata-Version: 2.1
Name: draw-with-percentage
Version: 0.0.6
Summary: Python Library to draw with percentage
Home-page: https://github.com/MatEE404/draw-with-percentage
Author: Mateusz Kołodziejczyk
Author-email: mateusz.j.kolodziejczyk@gmail.com
License: MIT
Platform: UNKNOWN
Classifier: Programming Language :: Python :: 3
Classifier: Programming Language :: Python :: 3.3
Classifier: Programming Language :: Python :: 3.4
Classifier: Programming Language :: Python :: 3.5
Classifier: Programming Language :: Python :: 3.6
Classifier: Programming Language :: Python :: 3.8
Classifier: License :: OSI Approved :: MIT License
Classifier: Operating System :: OS Independent
Requires-Python: >=3
